pygdelt/__init__.py
pygdelt/gdelt_base.py
pygdelt/gdeltv1.py
pygdelt/gdeltv2.py
pygdelt/tests/__init__.py
pygdelt/tests/test_gdelt_base.py
pygdelt/tests/test_gdeltv1.py
pygdelt/tests/test_gdeltv2.py
pygdelt-0.0.1a1.dist-info/DESCRIPTION.rst
pygdelt-0.0.1a1.dist-info/LICENSE.txt
pygdelt-0.0.1a1.dist-info/METADATA
pygdelt-0.0.1a1.dist-info/RECORD
pygdelt-0.0.1a1.dist-info/WHEEL
pygdelt-0.0.1a1.dist-info/metadata.json
pygdelt-0.0.1a1.dist-info/top_level.txt
